pynhc2/__init__.py
pynhc2/devicecontrol.py
pynhc2/mqttconnector.py
pynhc2/nhc2filereader.py
pynhc2-0.1.1.dist-info/licenses/LICENSE
pynhc2-0.1.1.dist-info/METADATA
pynhc2-0.1.1.dist-info/WHEEL
pynhc2-0.1.1.dist-info/top_level.txt
pynhc2-0.1.1.dist-info/RECORD
