Metadata-Version: 2.4
Name: pynhc2
Version: 0.1.1
Summary: Python SDK for Niko Home Control 2
Author-email: Kevin Ghekiere <kevinghekiere@gmail.com>
Maintainer-email: Kevin Ghekiere <kevinghekiere@gmail.com>
License: MIT License
Keywords: niko,home control,mqtt
Classifier: License :: OSI Approved :: MIT License
Classifier: Operating System :: OS Independent
Classifier: Programming Language :: Python
Classifier: Programming Language :: Python :: 3
Requires-Python: >=3.11
License-File: LICENSE
Requires-Dist: paho-mqtt>=2.1.0
Requires-Dist: setuptools>=80.9.0
Dynamic: license-file
